LICENSE.txt
README.md
setup.py
pywong/__init__.py
pywong.egg-info/PKG-INFO
pywong.egg-info/SOURCES.txt
pywong.egg-info/dependency_links.txt
pywong.egg-info/requires.txt
pywong.egg-info/top_level.txt
pywong/app/__init__.py
pywong/app/db_tools.py
pywong/db/__init__.py
pywong/db/settings.py
pywong/db/mssql/__init__.py
pywong/db/mssql/settings.py
pywong/db/mssql/utils.py
pywong/db/mysql/__init__.py
pywong/db/mysql/settings.py
pywong/db/mysql/utils.py
pywong/db/postgresql/__init__.py
pywong/db/postgresql/settings.py
pywong/db/postgresql/utils.py
pywong/ml/__init__.py
pywong/ml/preprocessing/__init__.py
pywong/ml/preprocessing/abnormal_cof.py
pywong/ml/sk/__init__.py
pywong/ml/sk/knn.py
pywong/ml/sk/linear_regression.py
pywong/ml/sk/random_forest.py
pywong/ml/sk/time_series.py
pywong/monitor/__init__.py
pywong/monitor/resource_monitor.py