Metadata-Version: 2.1
Name: pywong
Version: 3.1.0
Summary: pywong工具模块.
Home-page: https://blog.csdn.net/qq_16284479?type=blog
Author: ghy
Author-email: 1563713769@qq.com
License: Apache-2.0 license
Platform: all
Classifier: Programming Language :: Python :: 3
Classifier: Intended Audience :: Developers
Requires-Python: >=3.8
License-File: LICENSE.txt
